[
  {
    "crn": "12345",
    "section_code": "001",
    "meeting_days": "MWF",
    "meeting_time": "10:30AM-11:20AM",
    "instructor": "Dr. Smith",
    "term": "Fall 2024"
  },
  {
    "crn": "12346",
    "section_code": "002",
    "meeting_days": "MWF",
    "meeting_time": "11:30AM-12:20PM",
    "instructor": "Dr. Johnson",
    "term": "Fall 2024"
  },
  {
    "crn": "12347",
    "section_code": "003",
    "meeting_days": "TTh",
    "meeting_time": "9:00AM-10:15AM",
    "instructor": "Dr. Williams",
    "term": "Fall 2024"
  },
  {
    "crn": "12348",
    "section_code": "001",
    "meeting_days": "MWF",
    "meeting_time": "1:30PM-2:20PM",
    "instructor": "Dr. Brown",
    "term": "Fall 2024"
  },
  {
    "crn": "12349",
    "section_code": "002",
    "meeting_days": "TTh",
    "meeting_time": "2:30PM-3:45PM",
    "instructor": "Dr. Davis",
    "term": "Fall 2024"
  },
  {
    "crn": "12350",
    "section_code": "001",
    "meeting_days": "MWF",
    "meeting_time": "8:30AM-9:20AM",
    "instructor": "Dr. Wilson",
    "term": "Fall 2024"
  },
  {
    "crn": "12351",
    "section_code": "002",
    "meeting_days": "TTh",
    "meeting_time": "10:30AM-11:45AM",
    "instructor": "Dr. Moore",
    "term": "Fall 2024"
  },
  {
    "crn": "12352",
    "section_code": "001",
    "meeting_days": "MWF",
    "meeting_time": "12:30PM-1:20PM",
    "instructor": "Dr. Taylor",
    "term": "Fall 2024"
  },
  {
    "crn": "12353",
    "section_code": "002",
    "meeting_days": "TTh",
    "meeting_time": "1:30PM-2:45PM",
    "instructor": "Dr. Anderson",
    "term": "Fall 2024"
  },
  {
    "crn": "12354",
    "section_code": "001",
    "meeting_days": "MWF",
    "meeting_time": "2:30PM-3:20PM",
    "instructor": "Dr. Thomas",
    "term": "Fall 2024"
  },
  {
    "crn": "12355",
    "section_code": "002",
    "meeting_days": "TTh",
    "meeting_time": "3:30PM-4:45PM",
    "instructor": "Dr. Jackson",
    "term": "Fall 2024"
  },
  {
    "crn": "12356",
    "section_code": "001",
    "meeting_days": "MWF",
    "meeting_time": "4:30PM-5:20PM",
    "instructor": "Dr. White",
    "term": "Fall 2024"
  }
]
